ya_market_api/__init__.py
ya_market_api/async_api.py
ya_market_api/const.py
ya_market_api/exception.py
ya_market_api/sync_api.py
ya_market_api/base/__init__.py
ya_market_api/base/api.py
ya_market_api/base/async_api_mixin.py
ya_market_api/base/async_config.py
ya_market_api/base/config.py
ya_market_api/base/const.py
ya_market_api/base/convert.py
ya_market_api/base/enum_toolkit.py
ya_market_api/base/router.py
ya_market_api/base/sync_api_mixin.py
ya_market_api/base/sync_config.py
ya_market_api/base/dataclass/__init__.py
ya_market_api/base/dataclass/base_response.py
ya_market_api/base/dataclass/flipping_pager.py
ya_market_api/base/dataclass/gps.py
ya_market_api/base/dataclass/region.py
ya_market_api/campaign/__init__.py
ya_market_api/campaign/async_api.py
ya_market_api/campaign/base_api.py
ya_market_api/campaign/const.py
ya_market_api/campaign/router.py
ya_market_api/campaign/sync_api.py
ya_market_api/campaign/dataclass/__init__.py
ya_market_api/campaign/dataclass/campaign_list.py
ya_market_api/feedback/__init__.py
ya_market_api/feedback/async_api.py
ya_market_api/feedback/base_api.py
ya_market_api/feedback/const.py
ya_market_api/feedback/router.py
ya_market_api/feedback/sync_api.py
ya_market_api/feedback/dataclass/__init__.py
ya_market_api/feedback/dataclass/comment_add.py
ya_market_api/feedback/dataclass/comment_delete.py
ya_market_api/feedback/dataclass/comment_list.py
ya_market_api/feedback/dataclass/comment_update.py
ya_market_api/feedback/dataclass/generic.py
ya_market_api/feedback/dataclass/list.py
ya_market_api/feedback/dataclass/reaction_skip.py
ya_market_api/generic/__init__.py
ya_market_api/generic/functools.py
ya_market_api/generic/requests/__init__.py
ya_market_api/generic/requests/auth.py
ya_market_api/guide/__init__.py
ya_market_api/guide/async_api.py
ya_market_api/guide/base_api.py
ya_market_api/guide/router.py
ya_market_api/guide/sync_api.py
ya_market_api/guide/dataclass/__init__.py
ya_market_api/guide/dataclass/delivery_services.py
ya_market_api-2.0.1.dist-info/METADATA
ya_market_api-2.0.1.dist-info/WHEEL
ya_market_api-2.0.1.dist-info/licenses/LICENSE
ya_market_api-2.0.1.dist-info/RECORD
