Metadata-Version: 2.4
Name: ya-market-api
Version: 2.0.1
Summary: Yandex.Market seller API client
Author-email: Kirill_Lekhov <kirill.lekhov@mail.ru>
License: MIT License
License-File: LICENSE
Requires-Python: >=3.8.1
Requires-Dist: arrow>=1.3.0
Requires-Dist: pydantic>=2.10.6
Provides-Extra: all
Requires-Dist: aiohttp>=3.10.11; extra == 'all'
Requires-Dist: requests>=2.32.4; extra == 'all'
Provides-Extra: async
Requires-Dist: aiohttp>=3.10.11; extra == 'async'
Provides-Extra: sync
Requires-Dist: requests>=2.32.4; extra == 'sync'
